Metadata-Version: 2.1
Name: folder-structure
Version: 0.1.5
Summary: A simple folder structure creator.
Home-page: https://github.com/dvswells/folder-structure
Author: David Sanchez
Author-email: dvswells@gmail.com
License: 3-clause BSD
Keywords: folder,structure,file,ordering
Platform: any
Classifier: Development Status :: 4 - Beta
Classifier: Environment :: Console
Classifier: Intended Audience :: End Users/Desktop
Classifier: License :: OSI Approved :: BSD License
Classifier: Programming Language :: Python :: 3.8
Classifier: Topic :: Utilities
